LICENSE
MANIFEST.in
README.rst
requirements.txt
setup.cfg
setup.py
versioneer.py
s3clumper/__init__.py
s3clumper/_version.py
s3clumper/cmd.py
s3clumper/cmdio.py
s3clumper/main.py
s3clumper.egg-info/PKG-INFO
s3clumper.egg-info/SOURCES.txt
s3clumper.egg-info/dependency_links.txt
s3clumper.egg-info/entry_points.txt
s3clumper.egg-info/requires.txt
s3clumper.egg-info/top_level.txt
s3clumper.egg-info/zip-safe